ChangeLog.txt
LICENSE.txt
MANIFEST.in
README.rst
setup.py
safedexml/__init__.py
safedexml/fields.py
safedexml/test.py
safedexml.egg-info/PKG-INFO
safedexml.egg-info/SOURCES.txt
safedexml.egg-info/dependency_links.txt
safedexml.egg-info/requires.txt
safedexml.egg-info/top_level.txt