Metadata-Version: 1.1
Name: safedexml
Version: 0.5.1
Summary: a defusedxml version of dead-simple Object-XML mapper for Python
Home-page: http://packages.python.org/dexml
Author: Ryan Kelly
Author-email: ryan@rfk.id.au
License: MIT
Keywords: xml
Platform: UNKNOWN
Classifier: Programming Language :: Python
Classifier: Programming Language :: Python :: 2
Classifier: Programming Language :: Python :: 2.5
Classifier: Programming Language :: Python :: 2.6
Classifier: Programming Language :: Python :: 2.7
Classifier: Programming Language :: Python :: 3
Classifier: Programming Language :: Python :: 3.2
Classifier: License :: OSI Approved
Classifier: License :: OSI Approved :: MIT License
Classifier: Development Status :: 5 - Production/Stable
Classifier: Intended Audience :: Developers
Classifier: Topic :: Text Processing
Classifier: Topic :: Text Processing :: Markup
Classifier: Topic :: Text Processing :: Markup :: XML
Requires: defusedxml
